{"tunings":[{"type":"tone_chord","notes":[{"type":"tone_note","id":4,"sharps":0,"octave":0},{"type":"tone_note","id":0,"sharps":0,"octave":0},{"type":"tone_note","id":3,"sharps":0,"octave":0},{"type":"tone_note","id":6,"sharps":0,"octave":0},{"type":"tone_note","id":1,"sharps":0,"octave":0},{"type":"tone_note","id":4,"sharps":0,"octave":1}],"name":"E Standard"},{"type":"tone_chord","notes":[{"type":"tone_note","id":3,"sharps":0,"octave":0},{"type":"tone_note","id":0,"sharps":0,"octave":0},{"type":"tone_note","id":3,"sharps":0,"octave":0},{"type":"tone_note","id":6,"sharps":0,"octave":0},{"type":"tone_note","id":1,"sharps":0,"octave":0},{"type":"tone_note","id":4,"sharps":0,"octave":1}],"name":"Drop D"}],"current_tuning":1,"chords":[{"type":"interval_chord","notes":[{"type":"interval_note","id":0,"sharps":0,"octave":0},{"type":"interval_note","id":2,"sharps":0,"octave":0},{"type":"interval_note","id":4,"sharps":0,"octave":0}],"name":"Major","symbol":"","aliases":["M"]},{"type":"interval_chord","notes":[{"type":"interval_note","id":0,"sharps":0,"octave":0},{"type":"interval_note","id":2,"sharps":-1,"octave":0},{"type":"interval_note","id":4,"sharps":0,"octave":0}],"name":"minor","symbol":"m","aliases":[""]}],"current_chord":0,"favorites_groups":{"6449bbbf-6046-3b18-af37-e2e7eab69bee":{"favorites":{"a895b426-09e5-3394-a693-652482e908dd":{"span":3,"strings":[0,2,2,1,0,0],"lowest_string":0,"first_note":{"type":"interval_note","id":0,"sharps":0,"octave":0},"uuid":"a895b426-09e5-3394-a693-652482e908dd"},"82cd593e-d1e0-348b-bb44-0014f4edbcf7":{"span":3,"strings":[0,0,2,2,2,0],"lowest_string":0,"first_note":{"type":"interval_note","id":4,"sharps":0,"octave":-1},"uuid":"82cd593e-d1e0-348b-bb44-0014f4edbcf7"}},"uuid":"6449bbbf-6046-3b18-af37-e2e7eab69bee"},"d01018e1-df85-3b78-b53e-fa07f813f096":{"favorites":{},"uuid":"d01018e1-df85-3b78-b53e-fa07f813f096"},"31312b7f-a7d0-3270-b5a3-e944a4d8f5a8":{"favorites":{"032e2e4b-acd0-34db-b7ea-1c41e967310b":{"span":1,"strings":[0,-1,-1,0,0,0],"lowest_string":0,"first_note":{"type":"interval_note","id":0,"sharps":0,"octave":0},"uuid":"032e2e4b-acd0-34db-b7ea-1c41e967310b"}},"uuid":"31312b7f-a7d0-3270-b5a3-e944a4d8f5a8"},"f3c8034f-5dd9-3dab-b1de-0095677a8cf8":{"favorites":{"2d607732-3e78-3e1a-a26c-b4a18ac6cb2d":{"span":3,"strings":[2,2,2,1,0,0],"lowest_string":4,"first_note":{"type":"interval_note","id":4,"sharps":0,"octave":-1},"uuid":"2d607732-3e78-3e1a-a26c-b4a18ac6cb2d"}},"uuid":"f3c8034f-5dd9-3dab-b1de-0095677a8cf8"},"c5d1642c-640e-3793-9284-1caca9860bb1":{"favorites":{},"uuid":"c5d1642c-640e-3793-9284-1caca9860bb1"}},"preferences":{"left_handed":false,"neck_frets":24,"panel_frets":6,"main_bounds":[127,141,573,439],"tuning_bounds":[230,199,320,211],"chords_bounds":[150,150,490,258],"preferences_bounds":[191,185,187,183]}}